MANIFEST.in
setup.py
bin/pytaillog
pytaillog/__init__.py
pytaillog/server.py
pytaillog.egg-info/PKG-INFO
pytaillog.egg-info/SOURCES.txt
pytaillog.egg-info/dependency_links.txt
pytaillog.egg-info/not-zip-safe
pytaillog.egg-info/requires.txt
pytaillog.egg-info/top_level.txt
pytaillog/static/css/style.css
pytaillog/static/images/GitHub-Mark-64px.png
pytaillog/static/images/GitHub-Mark-Light-64px.png
pytaillog/templates/index.html