Metadata-Version: 1.1
Name: pytaillog
Version: 0.3
Summary: dispaly log in a browser
Home-page: https://github.com/lovedboy/PyTailLog
Author: lovedboy
Author-email: lovedboy.tk@qq.com
License: BSD
Platform: UNKNOWN
Classifier: License :: OSI Approved :: MIT License
Classifier: Programming Language :: Python
Classifier: Intended Audience :: Developers
Classifier: Operating System :: OS Independent
